pycoils/__init__.py
pycoils/common.py
pycoils/examples/BinarySearchTree.py
pycoils/examples/BitVector.py
pycoils/examples/ChainedHashTable.py
pycoils/examples/DisjointSetWithUnion.py
pycoils/examples/DoublyLinkedList.py
pycoils/examples/Heap.py
pycoils/examples/InternStore.py
pycoils/examples/LinkedList.py
pycoils/examples/Queue.py
pycoils/examples/SplayTree.py
pycoils/examples/Stack.py
pycoils/examples/__init__.py
pycoils/hashtables/HashTables.py
pycoils/hashtables/__init__.py
pycoils/hashtables/hashbuckets.py
pycoils/lists/__init__.py
pycoils/lists/doubly_linked_list.py
pycoils/lists/singly_linked_list.py
pycoils/misc/__init__.py
pycoils/misc/bit_vector.py
pycoils/misc/internstore.py
pycoils/sets/__init__.py
pycoils/sets/disjoint_sets_with_union.py
pycoils/stackNqueues/__init__.py
pycoils/stackNqueues/priorityqueue.py
pycoils/stackNqueues/queue.py
pycoils/stackNqueues/stack.py
pycoils/tests/__init__.py
pycoils/tests/data/__init__.py
pycoils/tests/data/testdata.py
pycoils/tests/disjoint_sets_with_union/__init__.py
pycoils/tests/disjoint_sets_with_union/test_disjoint_set_with_union.py
pycoils/tests/hashtables/__init__.py
pycoils/tests/hashtables/test_bst_seperate_chained_hash_table.py
pycoils/tests/hashtables/test_hash_bucket_as_bst.py
pycoils/tests/hashtables/test_hash_bucket_as_list.py
pycoils/tests/hashtables/test_hash_bucket_as_splayed.py
pycoils/tests/hashtables/test_linked_list_seperate_chain_hash_table.py
pycoils/tests/hashtables/test_splayed_seperate_chained_hash_table.py
pycoils/tests/lists/__init__.py
pycoils/tests/lists/test_doubly_linked_list.py
pycoils/tests/lists/test_linked_list.py
pycoils/tests/misc/__init__.py
pycoils/tests/misc/internstore.py
pycoils/tests/misc/test_bit_vector.py
pycoils/tests/stackNqueues/__init__.py
pycoils/tests/stackNqueues/priority_q_with_min_heap.py
pycoils/tests/stackNqueues/test_priority_q_entry.py
pycoils/tests/stackNqueues/test_priority_q_with_max_heap.py
pycoils/tests/stackNqueues/test_queue_with_list.py
pycoils-3.0.1.dist-info/LICENSE
pycoils-3.0.1.dist-info/METADATA
pycoils-3.0.1.dist-info/WHEEL
pycoils-3.0.1.dist-info/top_level.txt
pycoils-3.0.1.dist-info/RECORD
