Metadata-Version: 2.1
Name: pycoils
Version: 3.0.1
Summary: A Python datastructure library
Home-page: https://github.com/harisankar-krishna-swamy/coils.git
Author: Harisankar Krishna Swamy
Author-email: harisankar.krishna@outlook.com
License: Apache2
Platform: UNKNOWN
Classifier: Programming Language :: Python :: 3
Classifier: License :: OSI Approved :: Apache Software License
Classifier: Operating System :: OS Independent
Requires-Python: >=3.7.4, <4
